csvcatalog/__init__.py
csvcatalog/app.py
csvcatalog/config.py
csvcatalog/crypto.py
csvcatalog/main.py
csvcatalog/storage.py
csvcatalog/utils.py
csvcatalog/commands/__init__.py
csvcatalog/commands/base.py
csvcatalog/commands/delete.py
csvcatalog/commands/export.py
csvcatalog/commands/extract.py
csvcatalog/commands/filters.py
csvcatalog/commands/purge.py
csvcatalog/commands/search.py
csvcatalog/commands/settings.py
csvcatalog/commands/sql.py
csvcatalog/commands/tables.py
csvcatalog-2.20.dist-info/licenses/LICENSE
csvcatalog-2.20.dist-info/METADATA
csvcatalog-2.20.dist-info/WHEEL
csvcatalog-2.20.dist-info/entry_points.txt
csvcatalog-2.20.dist-info/top_level.txt
csvcatalog-2.20.dist-info/RECORD
