Metadata-Version: 2.4
Name: csvcatalog
Version: 2.20
Summary: tool for creating catalog from .csv tables in sqlite storage
License-Expression: MIT
Keywords: csv,catalog,sqlite,storage,data,dump
Requires-Python: >=3.13
License-File: LICENSE
Requires-Dist: platformdirs>=4.5.1
Requires-Dist: pycryptodome>=3.23.0
Requires-Dist: pydantic>=2.12.5
Requires-Dist: questionary>=2.1.1
Requires-Dist: rich>=14.2.0
Requires-Dist: typer>=0.20.0
Dynamic: license-file
